netinfo/__init__.py
netinfo/cli/__init__.py
netinfo/cli/client.py
netinfo/utils/__init__.py
netinfo-0.0.2.dist-info/DESCRIPTION.rst
netinfo-0.0.2.dist-info/METADATA
netinfo-0.0.2.dist-info/RECORD
netinfo-0.0.2.dist-info/WHEEL
netinfo-0.0.2.dist-info/entry_points.txt
netinfo-0.0.2.dist-info/metadata.json
netinfo-0.0.2.dist-info/top_level.txt
