Metadata-Version: 2.0
Name: netinfo
Version: 0.0.2
Summary: Client to interact with Netinfo services.
Home-page: UNKNOWN
Author: Brandon Dixon
Author-email: brandon@backscatter.io
License: MIT
Keywords: internet scanning,cybersecurity,defense,intelligence
Platform: UNKNOWN
Classifier: Development Status :: 4 - Beta
Classifier: Intended Audience :: Developers
Classifier: License :: OSI Approved :: MIT License
Classifier: Natural Language :: English
Classifier: Programming Language :: Python
Classifier: Topic :: Software Development :: Libraries
Classifier: Topic :: Security
Requires-Dist: requests
